setup.py
django_fluentd_requests_logging.egg-info/PKG-INFO
django_fluentd_requests_logging.egg-info/SOURCES.txt
django_fluentd_requests_logging.egg-info/dependency_links.txt
django_fluentd_requests_logging.egg-info/not-zip-safe
django_fluentd_requests_logging.egg-info/requires.txt
django_fluentd_requests_logging.egg-info/top_level.txt
fluentd/__init__.py
fluentd/middleware.py